Metadata-Version: 2.1
Name: proyecto-modulo
Version: 0.0.1
Summary: paquete de prueba para una clase de programacion
Home-page: https://github.com/Cesar-Crespo/proyecto-modulo.git
Author: Cesar Crespo
Author-email: cesar2crespo@gmail.com
License: MIT
License-File: LICENSE
